Metadata-Version: 1.0
Name: hardik-distributions
Version: 0.1
Summary: Gaussian and Binomial distributions
Home-page: UNKNOWN
Author: Hardik Jain
Author-email: hardikjain249@gmail.com
License: UNKNOWN
Platform: UNKNOWN
